minevent/__init__.py
minevent/conditions.py
minevent/handlers.py
minevent/manager.py
minevent/py.typed
minevent-0.5.0.dist-info/METADATA
minevent-0.5.0.dist-info/WHEEL
minevent-0.5.0.dist-info/licenses/LICENSE
minevent-0.5.0.dist-info/RECORD
